[
  {"id": "q01", "text": "PostgreSQL pool size configuration", "relevant": {"e001": 2, "e021": 2, "e011": 1}, "distractors": ["eD01"]},
  {"id": "q02", "text": "PostgreSQL pool timeout settings", "relevant": {"e023": 2, "e026": 1, "e027": 1}, "distractors": ["eD01"]},
  {"id": "q03", "text": "PostgreSQL connection pool configuration guide", "relevant": {"e001": 2, "e021": 2, "e011": 2, "e006": 1}, "distractors": ["eD01", "eD02"]},
  {"id": "q04", "text": "Django DATABASES connection pool setup", "relevant": {"e006": 2, "e007": 2, "e010": 1, "e008": 1}, "distractors": ["eD01"]},
  {"id": "q05", "text": "psycopg3 ConnectionPool usage", "relevant": {"e008": 2, "e009": 2, "e006": 1}, "distractors": ["eD01"]},
  {"id": "q06", "text": "PgBouncer transaction pool_mode configuration", "relevant": {"e011": 2, "e012": 2, "e015": 1, "e002": 1}, "distractors": ["eD01"]},
  {"id": "q07", "text": "PgBouncer prepared statements configuration", "relevant": {"e014": 2, "e002": 2, "e012": 1}, "distractors": ["eD01"]},
  {"id": "q08", "text": "pgpool-II vs PgBouncer for PostgreSQL pooling", "relevant": {"e016": 2, "e017": 1, "e019": 1, "e011": 1}, "distractors": ["eD01"]},
  {"id": "q09", "text": "SQLAlchemy pool_size max_overflow settings", "relevant": {"e021": 2, "e024": 1, "e025": 1}, "distractors": ["eD01"]},
  {"id": "q10", "text": "PostgreSQL pool exhausted error", "relevant": {"e036": 2, "e037": 2, "e027": 1}, "distractors": ["eD01"]},
  {"id": "q11", "text": "Heroku PostgreSQL connection pool limit", "relevant": {"e031": 2, "e032": 2}, "distractors": ["eD01"]},
  {"id": "q12", "text": "Fly.io multi-region Postgres pool", "relevant": {"e033": 2}, "distractors": ["eD01"]},
  {"id": "q13", "text": "asyncpg connection timeout configuration", "relevant": {"e003": 2, "e026": 1, "e027": 1, "e001": 1}, "distractors": ["eD01"]},
  {"id": "q14", "text": "PostgreSQL SSL connection configuration", "relevant": {"e028": 2, "e029": 2}, "distractors": ["eD01"]},
  {"id": "q15", "text": "Retry transient Postgres connection errors", "relevant": {"e030": 2, "e022": 1}, "distractors": ["eD01"]},
  {"id": "q16", "text": "Connection pool metrics monitoring", "relevant": {"e038": 2, "e039": 2, "e040": 1}, "distractors": ["eD01"]},
  {"id": "q17", "text": "Cloud Run Postgres IAM authentication configuration", "relevant": {"e034": 2, "e035": 2}, "distractors": ["eD01"]},
  {"id": "q18", "text": "Django read replica connection pool routing", "relevant": {"e006": 1, "e018": 2, "e033": 1}, "distractors": ["eD01"]},
  {"id": "q19", "text": "Default SQLAlchemy pool_size setting", "relevant": {"e021": 2, "e024": 1}, "distractors": ["eD01"]},
  {"id": "q20", "text": "asyncpg vs psycopg3 benchmarks", "relevant": {"e001": 2, "e008": 2, "e009": 2}, "distractors": ["eD01"]},
  {"id": "q21", "text": "Transactional outbox with PostgreSQL connections", "relevant": {"e041": 2, "e010": 1}, "distractors": ["eD01"]},
  {"id": "q22", "text": "Connection pool exhaustion during migrations", "relevant": {"e036": 2, "e037": 2, "e027": 1}, "distractors": ["eD01"]},
  {"id": "q23", "text": "Graceful connection draining on deploy", "relevant": {"e042": 2, "e032": 1}, "distractors": ["eD01"]},
  {"id": "q24", "text": "pool_mode session vs transaction in PgBouncer", "relevant": {"e012": 2, "e011": 1, "e013": 1}, "distractors": ["eD01"]},
  {"id": "q25", "text": "Health check for Postgres connection pool", "relevant": {"e038": 2, "e022": 1}, "distractors": ["eD01"]},
  {"id": "q26", "text": "statement_timeout and idle_in_transaction_session_timeout", "relevant": {"e026": 2, "e027": 2}, "distractors": ["eD01"]},
  {"id": "q27", "text": "Test database connection pooling with pytest", "relevant": {"e043": 2, "e022": 1}, "distractors": ["eD01"]},
  {"id": "q28", "text": "NOTIFY LISTEN PgBouncer pooling", "relevant": {"e013": 2, "e012": 1}, "distractors": ["eD01"]},
  {"id": "q29", "text": "Formula for PostgreSQL pool sizing", "relevant": {"e021": 2, "e036": 1, "e031": 1, "e002": 1}, "distractors": ["eD01"]},
  {"id": "q30", "text": "asyncpg pool graceful shutdown SIGTERM", "relevant": {"e042": 2, "e001": 1, "e005": 1}, "distractors": ["eD01"]}
]
